.long-description.html
README.rst
setup.py
src/collective/__init__.py
src/collective.base.egg-info/PKG-INFO
src/collective.base.egg-info/SOURCES.txt
src/collective.base.egg-info/dependency_links.txt
src/collective.base.egg-info/entry_points.txt
src/collective.base.egg-info/namespace_packages.txt
src/collective.base.egg-info/not-zip-safe
src/collective.base.egg-info/requires.txt
src/collective.base.egg-info/top_level.txt
src/collective/base/__init__.py
src/collective/base/adapter.py
src/collective/base/configure.zcml
src/collective/base/interfaces.py
src/collective/base/view.py
src/collective/base/viewlet.py
src/collective/base/viewletmanager.py
src/collective/base/tests/__init__.py
src/collective/base/tests/base.py
src/collective/base/tests/test_Adapter.py
src/collective/base/tests/test_BaseFormView.py
src/collective/base/tests/test_BaseView.py
src/collective/base/tests/test_RepeatedViewletManager.py
src/collective/base/tests/test_Viewlet.py
src/collective/base/viewletmanagers/repeated-viewlet-manager.pt
src/collective/base/views/base-form.pt
src/collective/base/views/base.pt