Metadata-Version: 1.1
Name: collective.base
Version: 0.7
Summary: Base class for plone with commonly used methods.
Home-page: https://github.com/taito/collective.base
Author: Taito Horiuchi
Author-email: taito.horiuchi@gmail.com
License: BSD
Platform: UNKNOWN
Classifier: Framework :: Plone
Classifier: Framework :: Plone :: 4.3
Classifier: License :: OSI Approved :: BSD License
Classifier: Programming Language :: Python
Classifier: Programming Language :: Python :: 2.7
